flopy/__init__.py
flopy/datbase.py
flopy/mbase.py
flopy/pakbase.py
flopy/version.py
flopy/discretization/__init__.py
flopy/discretization/grid.py
flopy/discretization/modeltime.py
flopy/discretization/structuredgrid.py
flopy/discretization/unstructuredgrid.py
flopy/discretization/vertexgrid.py
flopy/export/__init__.py
flopy/export/longnames.py
flopy/export/metadata.py
flopy/export/netcdf.py
flopy/export/shapefile_utils.py
flopy/export/unitsformat.py
flopy/export/utils.py
flopy/export/vtk.py
flopy/mf6/__init__.py
flopy/mf6/mfbase.py
flopy/mf6/mfmodel.py
flopy/mf6/mfpackage.py
flopy/mf6/mfsimbase.py
flopy/mf6/coordinates/__init__.py
flopy/mf6/coordinates/modeldimensions.py
flopy/mf6/coordinates/modelgrid.py
flopy/mf6/coordinates/simulationtime.py
flopy/mf6/data/__init__.py
flopy/mf6/data/mfdata.py
flopy/mf6/data/mfdataarray.py
flopy/mf6/data/mfdatalist.py
flopy/mf6/data/mfdataplist.py
flopy/mf6/data/mfdatascalar.py
flopy/mf6/data/mfdatastorage.py
flopy/mf6/data/mfdatautil.py
flopy/mf6/data/mffileaccess.py
flopy/mf6/data/mfstructure.py
flopy/mf6/modflow/__init__.py
flopy/mf6/modflow/mfems.py
flopy/mf6/modflow/mfgnc.py
flopy/mf6/modflow/mfgwe.py
flopy/mf6/modflow/mfgweadv.py
flopy/mf6/modflow/mfgwecnd.py
flopy/mf6/modflow/mfgwectp.py
flopy/mf6/modflow/mfgwedis.py
flopy/mf6/modflow/mfgwedisu.py
flopy/mf6/modflow/mfgwedisv.py
flopy/mf6/modflow/mfgweesl.py
flopy/mf6/modflow/mfgweest.py
flopy/mf6/modflow/mfgwefmi.py
flopy/mf6/modflow/mfgwegwe.py
flopy/mf6/modflow/mfgweic.py
flopy/mf6/modflow/mfgwelke.py
flopy/mf6/modflow/mfgwemve.py
flopy/mf6/modflow/mfgwemwe.py
flopy/mf6/modflow/mfgwenam.py
flopy/mf6/modflow/mfgweoc.py
flopy/mf6/modflow/mfgwesfe.py
flopy/mf6/modflow/mfgwessm.py
flopy/mf6/modflow/mfgweuze.py
flopy/mf6/modflow/mfgwf.py
flopy/mf6/modflow/mfgwfapi.py
flopy/mf6/modflow/mfgwfbuy.py
flopy/mf6/modflow/mfgwfchd.py
flopy/mf6/modflow/mfgwfcsub.py
flopy/mf6/modflow/mfgwfdis.py
flopy/mf6/modflow/mfgwfdisu.py
flopy/mf6/modflow/mfgwfdisv.py
flopy/mf6/modflow/mfgwfdrn.py
flopy-3.9.5.dist-info/METADATA
flopy-3.9.5.dist-info/WHEEL
flopy-3.9.5.dist-info/entry_points.txt
flopy-3.9.5.dist-info/licenses/LICENSE.md
flopy-3.9.5.dist-info/RECORD
