Metadata-Version: 2.4
Name: flopy
Version: 3.9.5
Summary: FloPy is a Python package to create, run, and post-process MODFLOW-based models
Project-URL: Documentation, https://flopy.readthedocs.io
Project-URL: Release Notes, https://github.com/modflowpy/flopy/blob/develop/docs/version_changes.md
Project-URL: Bug Tracker, https://github.com/modflowpy/flopy/issues
Project-URL: Source Code, https://github.com/modflowpy/flopy
Author-email: FloPy Team <modflow@usgs.gov>
Maintainer-email: "Joseph D. Hughes" <jdhughes@usgs.gov>
License: CC0
License-File: LICENSE.md
Keywords: MODFLOW,groundwater,hydrogeology
Classifier: Development Status :: 5 - Production/Stable
Classifier: Intended Audience :: Science/Research
Classifier: License :: CC0 1.0 Universal (CC0 1.0) Public Domain Dedication
Classifier: Programming Language :: Python :: 3 :: Only
Classifier: Programming Language :: Python :: 3.10
Classifier: Programming Language :: Python :: 3.11
Classifier: Programming Language :: Python :: 3.12
Classifier: Programming Language :: Python :: 3.13
Classifier: Topic :: Scientific/Engineering :: Hydrology
Requires-Python: >=3.10
Requires-Dist: matplotlib>=1.4.0
Requires-Dist: numpy>=1.20.3
Requires-Dist: pandas>=2.0.0
Provides-Extra: codegen
Requires-Dist: boltons; extra == 'codegen'
Requires-Dist: jinja2>=3.0; extra == 'codegen'
Requires-Dist: modflow-devtools==1.7.0; extra == 'codegen'
Requires-Dist: tomli; extra == 'codegen'
Requires-Dist: tomli-w; extra == 'codegen'
Provides-Extra: dev
Requires-Dist: affine; extra == 'dev'
Requires-Dist: boltons; extra == 'dev'
Requires-Dist: cffconvert; extra == 'dev'
Requires-Dist: codespell[toml]>=2.2.2; extra == 'dev'
Requires-Dist: coverage!=7.6.5; extra == 'dev'
Requires-Dist: descartes; extra == 'dev'
Requires-Dist: filelock; extra == 'dev'
Requires-Dist: fiona; extra == 'dev'
Requires-Dist: flaky; extra == 'dev'
Requires-Dist: geojson; extra == 'dev'
Requires-Dist: geopandas; extra == 'dev'
Requires-Dist: gitpython; extra == 'dev'
Requires-Dist: h5py; extra == 'dev'
Requires-Dist: imageio; extra == 'dev'
Requires-Dist: ipython[kernel]; extra == 'dev'
Requires-Dist: jinja2>=3.0; extra == 'dev'
Requires-Dist: jupyter; extra == 'dev'
Requires-Dist: jupyter-client>=8.4.0; extra == 'dev'
Requires-Dist: jupytext; extra == 'dev'
Requires-Dist: modflow-devtools==1.7.0; extra == 'dev'
Requires-Dist: myst-parser; extra == 'dev'
Requires-Dist: nbconvert<7.14.0; extra == 'dev'
Requires-Dist: nbsphinx; extra == 'dev'
Requires-Dist: netcdf4; extra == 'dev'
Requires-Dist: pooch; extra == 'dev'
Requires-Dist: pymetis; (platform_system != 'Windows') and extra == 'dev'
Requires-Dist: pyproj; extra == 'dev'
Requires-Dist: pyshp; extra == 'dev'
Requires-Dist: pytest!=8.1.0; extra == 'dev'
Requires-Dist: pytest-benchmark; extra == 'dev'
Requires-Dist: pytest-cov; extra == 'dev'
Requires-Dist: pytest-dotenv; extra == 'dev'
Requires-Dist: pytest-xdist; extra == 'dev'
Requires-Dist: pyvista; extra == 'dev'
Requires-Dist: pyyaml; extra == 'dev'
Requires-Dist: pyzmq>=25.1.2; extra == 'dev'
Requires-Dist: rasterio; extra == 'dev'
Requires-Dist: rasterstats; extra == 'dev'
Requires-Dist: rtds-action; extra == 'dev'
Requires-Dist: ruff; extra == 'dev'
Requires-Dist: scikit-learn; extra == 'dev'
Requires-Dist: scipy; extra == 'dev'
Requires-Dist: shapely>=2.0; extra == 'dev'
Requires-Dist: sphinx-rtd-theme>=1; extra == 'dev'
Requires-Dist: sphinx==7.1.2; extra == 'dev'
Requires-Dist: syrupy<5.0.0; extra == 'dev'
Requires-Dist: tach; extra == 'dev'
Requires-Dist: tomli; extra == 'dev'
Requires-Dist: tomli-w; extra == 'dev'
Requires-Dist: virtualenv; extra == 'dev'
Requires-Dist: vtk>=9.4.0; extra == 'dev'
Requires-Dist: xmipy; extra == 'dev'
Provides-Extra: doc
Requires-Dist: affine; extra == 'doc'
Requires-Dist: descartes; extra == 'doc'
Requires-Dist: fiona; extra == 'doc'
Requires-Dist: geojson; extra == 'doc'
Requires-Dist: geopandas; extra == 'doc'
Requires-Dist: gitpython; extra == 'doc'
Requires-Dist: h5py; extra == 'doc'
Requires-Dist: imageio; extra == 'doc'
Requires-Dist: ipython[kernel]; extra == 'doc'
Requires-Dist: jupytext; extra == 'doc'
Requires-Dist: myst-parser; extra == 'doc'
Requires-Dist: nbconvert<7.14.0; extra == 'doc'
Requires-Dist: nbsphinx; extra == 'doc'
Requires-Dist: netcdf4; extra == 'doc'
Requires-Dist: pooch; extra == 'doc'
Requires-Dist: pymetis; (platform_system != 'Windows') and extra == 'doc'
Requires-Dist: pyproj; extra == 'doc'
Requires-Dist: pyshp; extra == 'doc'
Requires-Dist: pyvista; extra == 'doc'
Requires-Dist: pyyaml; extra == 'doc'
Requires-Dist: rasterio; extra == 'doc'
Requires-Dist: rasterstats; extra == 'doc'
Requires-Dist: rtds-action; extra == 'doc'
Requires-Dist: scikit-learn; extra == 'doc'
Requires-Dist: scipy; extra == 'doc'
Requires-Dist: shapely>=2.0; extra == 'doc'
Requires-Dist: sphinx-rtd-theme>=1; extra == 'doc'
Requires-Dist: sphinx==7.1.2; extra == 'doc'
Requires-Dist: vtk>=9.4.0; extra == 'doc'
Requires-Dist: xmipy; extra == 'doc'
Provides-Extra: lint
Requires-Dist: cffconvert; extra == 'lint'
Requires-Dist: codespell[toml]>=2.2.2; extra == 'lint'
Requires-Dist: ruff; extra == 'lint'
Provides-Extra: optional
Requires-Dist: affine; extra == 'optional'
Requires-Dist: descartes; extra == 'optional'
Requires-Dist: fiona; extra == 'optional'
Requires-Dist: geojson; extra == 'optional'
Requires-Dist: geopandas; extra == 'optional'
Requires-Dist: gitpython; extra == 'optional'
Requires-Dist: h5py; extra == 'optional'
Requires-Dist: imageio; extra == 'optional'
Requires-Dist: netcdf4; extra == 'optional'
Requires-Dist: pooch; extra == 'optional'
Requires-Dist: pymetis; (platform_system != 'Windows') and extra == 'optional'
Requires-Dist: pyproj; extra == 'optional'
Requires-Dist: pyshp; extra == 'optional'
Requires-Dist: pyvista; extra == 'optional'
Requires-Dist: rasterio; extra == 'optional'
Requires-Dist: rasterstats; extra == 'optional'
Requires-Dist: scikit-learn; extra == 'optional'
Requires-Dist: scipy; extra == 'optional'
Requires-Dist: shapely>=2.0; extra == 'optional'
Requires-Dist: vtk>=9.4.0; extra == 'optional'
Requires-Dist: xmipy; extra == 'optional'
Provides-Extra: test
Requires-Dist: boltons; extra == 'test'
Requires-Dist: cffconvert; extra == 'test'
Requires-Dist: codespell[toml]>=2.2.2; extra == 'test'
Requires-Dist: coverage!=7.6.5; extra == 'test'
Requires-Dist: filelock; extra == 'test'
Requires-Dist: flaky; extra == 'test'
Requires-Dist: jupyter; extra == 'test'
Requires-Dist: jupyter-client>=8.4.0; extra == 'test'
Requires-Dist: jupytext; extra == 'test'
Requires-Dist: modflow-devtools==1.7.0; extra == 'test'
Requires-Dist: pytest!=8.1.0; extra == 'test'
Requires-Dist: pytest-benchmark; extra == 'test'
Requires-Dist: pytest-cov; extra == 'test'
Requires-Dist: pytest-dotenv; extra == 'test'
Requires-Dist: pytest-xdist; extra == 'test'
Requires-Dist: pyzmq>=25.1.2; extra == 'test'
Requires-Dist: ruff; extra == 'test'
Requires-Dist: syrupy<5.0.0; extra == 'test'
Requires-Dist: tomli; extra == 'test'
Requires-Dist: tomli-w; extra == 'test'
Requires-Dist: virtualenv; extra == 'test'
